pyAsciiEngine/__init__.py
pyAsciiEngine/blank.py
pyAsciiEngine/demo_1.py
pyAsciiEngine/engine.py
pyAsciiEngine/engine_test.py
pyAsciiEngine/test.py
pyAsciiEngine-0.0.13.dist-info/METADATA
pyAsciiEngine-0.0.13.dist-info/WHEEL
pyAsciiEngine-0.0.13.dist-info/top_level.txt
pyAsciiEngine-0.0.13.dist-info/RECORD
